hydraclick/__init__.py
hydraclick/__main__.py
hydraclick/core.py
hydraclick/display_config.py
hydraclick/options.py
hydraclick/run.py
hydraclick/terminal_effects.py
hydraclick/version.py
hydraclick-0.0.8.dist-info/METADATA
hydraclick-0.0.8.dist-info/WHEEL
hydraclick-0.0.8.dist-info/entry_points.txt
hydraclick-0.0.8.dist-info/licenses/LICENSE
hydraclick-0.0.8.dist-info/RECORD
