Metadata-Version: 2.3
Name: hydraclick
Version: 0.0.8
Summary: Develop CLI tools with top-notch config management like a boss.
Author-email: Guillem Duran Ballester <guillem@fragile.tech>
Maintainer-email: Guillem Duran Ballester <guillem@fragile.tech>
License: MIT License
License-File: LICENSE
Keywords: CLI,config,hydra,omegaconf
Classifier: Development Status :: 3 - Alpha
Classifier: Topic :: Software Development :: Libraries :: Python Modules
Requires-Python: >=3.10
Requires-Dist: click>=8.1.7
Requires-Dist: hydra-core
Provides-Extra: all
Requires-Dist: flogging>=0.0.22; extra == 'all'
Requires-Dist: terminaltexteffects>=0.11.0; extra == 'all'
Provides-Extra: flogging
Requires-Dist: flogging>=0.0.22; extra == 'flogging'
Provides-Extra: terminaltexteffects
Requires-Dist: terminaltexteffects>=0.11.0; extra == 'terminaltexteffects'
Provides-Extra: test
Requires-Dist: hypothesis>=6.24.6; extra == 'test'
Requires-Dist: psutil>=5.8.0; extra == 'test'
Requires-Dist: pytest-cov>=3.0.0; extra == 'test'
Requires-Dist: pytest-rerunfailures>=10.2; extra == 'test'
Requires-Dist: pytest-xdist>=2.4.0; extra == 'test'
Requires-Dist: pytest>=6.2.5; extra == 'test'
Requires-Dist: pyvirtualdisplay>=1.3.2; extra == 'test'
Requires-Dist: tomli>=1.2.3; extra == 'test'
